bapp_api_client/__init__.py
bapp_api_client/api_client.py
bapp_api_client/configuration.py
bapp_api_client/helpers.py
bapp_api_client/rest.py
bapp_api_client/api/__init__.py
bapp_api_client/api/account_api.py
bapp_api_client/api/announcement_api.py
bapp_api_client/api/associate_loan_api.py
bapp_api_client/api/auto_api.py
bapp_api_client/api/bank_statement_api.py
bapp_api_client/api/business_api.py
bapp_api_client/api/cash_register_api.py
bapp_api_client/api/contract_api.py
bapp_api_client/api/custom_cargo_api.py
bapp_api_client/api/dataset_api.py
bapp_api_client/api/documentation_api.py
bapp_api_client/api/documents_api.py
bapp_api_client/api/domains_api.py
bapp_api_client/api/email_monitor_api.py
bapp_api_client/api/emenu_api.py
bapp_api_client/api/enki_api.py
bapp_api_client/api/external_affiliate_api.py
bapp_api_client/api/graveyard_api.py
bapp_api_client/api/iftt_api.py
bapp_api_client/api/offline_affiliation_api.py
bapp_api_client/api/online_payment_api.py
bapp_api_client/api/production_api.py
bapp_api_client/api/project_api.py
bapp_api_client/api/quality_api.py
bapp_api_client/api/receipt_api.py
bapp_api_client/api/rental_api.py
bapp_api_client/api/salary_api.py
bapp_api_client/api/services_api.py
bapp_api_client/api/shop_api.py
bapp_api_client/api/simple_stocks_api.py
bapp_api_client/api/sms_manager_api.py
bapp_api_client/api/stocks_api.py
bapp_api_client/api/supplier_order_api.py
bapp_api_client/api/support_api.py
bapp_api_client/api/task_api.py
bapp_api_client/api/timesheet_api.py
bapp_api_client/api/warehouse_api.py
bapp_api_client/models/__init__.py
bapp_api_client/models/accept_offer.py
bapp_api_client/models/accept_offer_item.py
bapp_api_client/models/acceptance.py
bapp_api_client/models/account.py
bapp_api_client/models/accounting_document.py
bapp_api_client/models/accounting_document_mark.py
bapp_api_client/models/address.py
bapp_api_client/models/adjustment_note_item_model.py
bapp_api_client/models/adjustment_note_model.py
bapp_api_client-1.1.22.dist-info/METADATA
bapp_api_client-1.1.22.dist-info/WHEEL
bapp_api_client-1.1.22.dist-info/top_level.txt
bapp_api_client-1.1.22.dist-info/RECORD
